pypcp/__init__.py
pypcp/pcp.py
pypcp/pcp_cli.py
pypcp/utils/__init__.py
pypcp/utils/pcp_md5.py
pypcp/utils/pcp_stream.py
pypcp-1.0.0rc1.dist-info/DESCRIPTION.rst
pypcp-1.0.0rc1.dist-info/METADATA
pypcp-1.0.0rc1.dist-info/RECORD
pypcp-1.0.0rc1.dist-info/WHEEL
pypcp-1.0.0rc1.dist-info/entry_points.txt
pypcp-1.0.0rc1.dist-info/metadata.json
pypcp-1.0.0rc1.dist-info/top_level.txt
