Metadata-Version: 2.0
Name: pypcp
Version: 1.0.0rc1
Summary: Pgpool-II Communication Protocol(PCP) library.
Home-page: https://github.com/uhayat/pypcp
Author: Umar Hayat
Author-email: m.umarkiani@gmail.com
Maintainer: Umar Hayat
Maintainer-email: m.umarkiani@gmail.com
License: PostgreSQL License
Project-URL: Source Code, https://github.com/uhayat/pypcp/
Project-URL: Issue Tracker, https://github.com/uhayat/pypcp/issues/
Platform: UNKNOWN
Classifier: Development Status :: 5 - Production/Stable
Classifier: Environment :: Other Environment
Classifier: Intended Audience :: Developers
Classifier: Intended Audience :: End Users/Desktop
Classifier: Intended Audience :: System Administrators
Classifier: License :: OSI Approved :: PostgreSQL License
Classifier: Operating System :: OS Independent
Classifier: Programming Language :: Python
Classifier: Topic :: Database
Classifier: Topic :: Utilities
Classifier: Topic :: Software Development :: Libraries :: Python Modules
Requires-Python: >= 3.6
